#######################################################################################################################################
<poster>Enoch Movies</poster>
#######################################################################################################################################


<item>
<title>2:22</title>
<meta>
<content>movie</content>
<imdb>tt1131724</imdb>
<title>2:22</title>
<year>2017</year>
</meta>
<link>
<sublink name="Stream 1 ">http://fastplay.cc/zl1fff4hajma.html</sublink>
<sublink name="Stream 2 ">https://www.rapidvideo.com/v/FH56M953QK</sublink>
<sublink name="Stream 3 ">search</sublink>
</link>
<thumbnail>https://images-na.ssl-images-amazon.com/images/M/MV5BNDQyMTUyMDExNl5BMl5BanBnXkFtZTgwODkxODEyMjI@._V1_SY1000_CR0,0,672,1000_AL_.jpg</thumbnail>
<fanart>https://images-na.ssl-images-amazon.com/images/M/MV5BYmQ0YTBiMDUtNTkxMC00MTAyLWIwMzYtZGRkZjNmODM4ZGQ3XkEyXkFqcGdeQXVyNjUxMjc1OTM@._V1_SX1777_CR0,0,1777,747_AL_.jpg</fanart>
</item>


<item>
<title>Wonder Woman</title>
<meta>
<content>movie</content>
<imdb>tt0451279</imdb>
<title>Wonder Woman</title>
<year>2017</year>
</meta>
<link>
<sublink name="Stream 1 ">http://fastplay.cc/zprghgpoqy6t.html</sublink>
<sublink name="Stream 2 ">https://www.rapidvideo.com/v/FH4UHECTW8</sublink>
<sublink name="Stream 3 ">search</sublink>
</link>
<thumbnail>https://images-na.ssl-images-amazon.com/images/M/MV5BNDFmZjgyMTEtYTk5MC00NmY0LWJhZjktOWY2MzI5YjkzODNlXkEyXkFqcGdeQXVyMDA4NzMyOA@@._V1_SY1000_SX675_AL_.jpg</thumbnail>
<fanart>https://fanart.tv/fanart/movies/297762/moviebackground/wonder-woman-58fa27775eaf1.jpg</fanart>
</item>


<item>
<title>CHIPS</title>
<meta>
<content>movie</content>
<imdb>tt0493405</imdb>
<title>CHIPS</title>
<year>2017</year>
</meta>
<link>
<sublink name="Stream 1 ">https://www.rapidvideo.com/v/FGKO25VPG9</sublink>
<sublink name="Stream 2 ">http://fastplay.cc/m9gwbt8xl427.html</sublink>
<sublink name="Stream 3 ">search</sublink>
</link>
<thumbnail>https://images-na.ssl-images-amazon.com/images/M/MV5BZTliN2IyMTctYTliOS00ZTJiLTkxN2YtNDg1YTJiZTA4MTVlL2ltYWdlXkEyXkFqcGdeQXVyMTkxNjUyNQ@@._V1_.jpg</thumbnail>
<fanart>https://fanart.tv/fanart/movies/417644/moviebackground/chips-58c0f1022f813.jpg</fanart>
</item>


<item>
<title>The Fate of the Furious</title>
<meta>
<content>movie</content>
<imdb>tt4630562</imdb>
<title>The Fate of the Furious</title>
<year>2017</year>
<info>When a mysterious woman seduces Dom into the world of terrorism and a betrayal of those closest to him, the crew face trials that will test them as never before.</info>
</meta>
<link>
<sublink name="Stream 1 ">http://fastplay.cc/nq22hzwruz43.html</sublink>
<sublink name="Stream 2 ">https://www.rapidvideo.com/v/FFQJWPQ7FG</sublink>
<sublink name="Stream 3 ">https://vidlox.tv/12zu2akm49ra</sublink>
<sublink name="Stream 4 ">search</sublink>
</link>
<thumbnail>https://images-na.ssl-images-amazon.com/images/M/MV5BMjMxODI2NDM5Nl5BMl5BanBnXkFtZTgwNjgzOTk1MTI@._V1_SY1000_CR0,0,631,1000_AL_.jpg</thumbnail>
<fanart>https://images-na.ssl-images-amazon.com/images/M/MV5BZmEzOTQyNDgtODE3ZC00MDkxLWJiZWUtMTUyMzJhMmQ2ZTkxXkEyXkFqcGdeQXVyMjQ1NjM4OTE@._V1_.jpg</fanart>
</item>


<item>
<title>Power Rangers</title>
<meta>
<content>movie</content>
<imdb>tt3717490</imdb>
<title>Power Rangers</title>
<year>2017</year>
</meta>
<link>
<sublink name="Stream 1 ">https://www.rapidvideo.com/v/FGKNPQ67QM</sublink>
<sublink name="Stream 2 ">http://fastplay.cc/mjf4b427ot6u.html</sublink>
<sublink name="Stream 3 ">search</sublink>
</link>
<thumbnail>https://images-na.ssl-images-amazon.com/images/M/MV5BMTU1MTkxNzc5NF5BMl5BanBnXkFtZTgwOTM2Mzk3MTI@._V1_SY1000_CR0,0,648,1000_AL_.jpg</thumbnail>
<fanart>https://fanart.tv/fanart/movies/305470/moviebackground/power-rangers-583f83e76ac08.jpg</fanart>
</item>


<item>
<title>John Wick: Chapter 2</title>
<meta>
<content>movie</content>
<imdb>tt4425200</imdb>
<title>John Wick: Chapter 2</title>
<year>2017</year>
</meta>
<link>
<sublink name="Stream 1 ">http://fastplay.cc/hmj2j2fsimd1.html</sublink>
<sublink name="Stream 2 ">search</sublink>
</link>
<thumbnail>https://images-na.ssl-images-amazon.com/images/M/MV5BMjE2NDkxNTY2M15BMl5BanBnXkFtZTgwMDc2NzE0MTI@._V1_SY1000_CR0,0,648,1000_AL_.jpg</thumbnail>
<fanart>https://images-na.ssl-images-amazon.com/images/M/MV5BMTc4OTIyODM0N15BMl5BanBnXkFtZTgwOTA5OTYxMDI@._V1_SX1500_CR0,0,1500,999_AL_.jpg</fanart>
</item>


<item>
<title>The LEGO Batman Movie</title>
<meta>
<content>movie</content>
<imdb>tt4116284</imdb>
<title>The LEGO Batman Movie</title>
<year>2017</year>
</meta>
<link>search</link>
<thumbnail>https://images-na.ssl-images-amazon.com/images/M/MV5BMTcyNTEyOTY0M15BMl5BanBnXkFtZTgwOTAyNzU3MDI@._V1_SY1000_CR0,0,674,1000_AL_.jpg</thumbnail>
<fanart>https://images-na.ssl-images-amazon.com/images/M/MV5BNWZlZGM4ZmYtMTc2ZS00Nzc4LWJiMGYtNzNiNmUxMGNlMjY3XkEyXkFqcGdeQXVyNDk0MTA4MTY@._V1_.jpg</fanart>
</item>


<item>
<title>Beauty and the Beast</title>
<meta>
<content>movie</content>
<imdb>tt2771200</imdb>
<title>Beauty and the Beast</title>
<year>2017</year>
</meta>
<link>
<sublink name="Stream 1 ">https://www.rapidvideo.com/v/FFRMQ3CCM1</sublink>
<sublink name="Stream 2 ">https://vidlox.tv/i2xc8dlhua91</sublink>
<sublink name="Stream 3 ">http://fastplay.cc/4h212fpmpjuf.html</sublink>
<sublink name="Stream 4 ">search</sublink>
</link>
<thumbnail>https://images-na.ssl-images-amazon.com/images/M/MV5BMTUwNjUxMTM4NV5BMl5BanBnXkFtZTgwODExMDQzMTI@._V1_SY1000_CR0,0,674,1000_AL_.jpg</thumbnail>
<fanart>https://images-na.ssl-images-amazon.com/images/M/MV5BMjI4MjE1MDE0Ml5BMl5BanBnXkFtZTgwNjcyMTkxMTI@._V1_.jpg</fanart>
</item>


<item>
<title>Life</title>
<meta>
<content>movie</content>
<imdb>tt5442430</imdb>
<title>Life</title>
<year>2017</year>
</meta>
<link>
<sublink name="Stream 1 ">http://fastplay.cc/2ta3gvdrje5p.html</sublink>
<sublink name="Stream 2 ">search</sublink>
</link>
<thumbnail>https://images-na.ssl-images-amazon.com/images/M/MV5BMzAwMmQxNTctYjVmYi00MDdlLWEzMWUtOTE5NTRiNDhhNjI2L2ltYWdlXkEyXkFqcGdeQXVyMTkxNjUyNQ@@._V1_SY1000_SX675_AL_.jpg</thumbnail>
<fanart>https://images-na.ssl-images-amazon.com/images/M/MV5BZjIyN2QwZTctNjRkNS00NjNiLTg0YzUtZjQyNDQxM2ZkYjZmL2ltYWdlXkEyXkFqcGdeQXVyNjUwNzk3NDc@._V1_SX1777_CR0,0,1777,852_AL_.jpg</fanart>
</item>


<item>
<title>Kidnap</title>
<meta>
<content>movie</content>
<imdb>tt1458169</imdb>
<title>Kidnap</title>
<year>2017</year>
</meta>
<link>
<sublink name="Stream 1 ">https://www.rapidvideo.com/v/FFRLNIQQ8L</sublink>
<sublink name="Stream 2 ">https://vidlox.tv/vh2yiqcyyp6d</sublink>
<sublink name="Stream 3 ">https://vidoza.net/6a03c4sd9568.html</sublink>
<sublink name="Stream 4 ">https://www.rapidvideo.com/v/FGLOTM4WTI</sublink>
<sublink name="Stream 5 ">search</sublink>
</link>
<thumbnail>https://images-na.ssl-images-amazon.com/images/M/MV5BMTkxNTAxNDg0OF5BMl5BanBnXkFtZTgwNTgzNTA4OTE@._V1_.jpg</thumbnail>
<fanart>https://image.tmdb.org/t/p/w533_and_h300_bestv2/swv004GAwu0Bi1nAHAEADIoGezM.jpg</fanart>
</item>


<item>
<title>The Boss Baby</title>
<meta>
<content>movie</content>
<imdb>tt3874544</imdb>
<title>The Boss Baby</title>
<year>2017</year>
</meta>
<link>
<sublink name="Stream 1 ">https://www.rapidvideo.com/v/FFRMK2PYMH</sublink>
<sublink name="Stream 2 ">https://vidlox.tv/88aodv1l2850</sublink>
<sublink name="Stream 3 ">http://fastplay.cc/wfnh8f1xkyep.html</sublink>
<sublink name="Stream 4 ">search</sublink>
</link>
<thumbnail>https://images-na.ssl-images-amazon.com/images/M/MV5BMTk2NjI5NzgwNl5BMl5BanBnXkFtZTgwNDc4NTA1OTE@._V1_SY1000_CR0,0,947,1000_AL_.jpg</thumbnail>
<fanart>https://images-na.ssl-images-amazon.com/images/M/MV5BOTQwODA4MTQtYjM2MS00YmExLTk0NWQtYWYwZDM1NGYxNGEyXkEyXkFqcGdeQXVyNDg2MjUxNjM@._V1_SX1777_CR0,0,1777,736_AL_.jpg</fanart>
</item>


<item>
<title>Fist Fight</title>
<meta>
<content>movie</content>
<imdb>tt3401882</imdb>
<title>Fist Fight</title>
<year>2017</year>
</meta>
<link>
<sublink name="Stream 1 ">https://www.rapidvideo.com/v/FFQK6095V1</sublink>
<sublink name="Stream 2 ">https://vidlox.tv/vfnaea5eup06</sublink>
<sublink name="Stream 3 ">search</sublink>
</link>
<thumbnail>https://i.imgur.com/L33CQQf.jpg</thumbnail>
<fanart>https://i.imgur.com/71DIWlV.jpg</fanart>
</item>


<item>
<title>Before I Fall</title>
<meta>
<content>movie</content>
<imdb>tt1691916	</imdb>
<title>Before I Fall</title>
<year>2017</year>
</meta>
<link>
<sublink name="Stream 1 ">https://www.rapidvideo.com/v/FFRSLSLGES</sublink>
<sublink name="Stream 2 ">https://vidlox.tv/8yleboimwqun</sublink>
<sublink name="Stream 3 ">search</sublink>
</link>
<thumbnail>https://images-na.ssl-images-amazon.com/images/M/MV5BNDYwOTY0MDI2OV5BMl5BanBnXkFtZTgwOTE5NzM2MDI@._V1_SY1000_SX675_AL_.jpg</thumbnail>
<fanart>https://images-na.ssl-images-amazon.com/images/M/MV5BZTNjYzljYjMtZjUxMi00ZWI3LWI4ZTktYjg0ZDY4ODNkNTcyXkEyXkFqcGdeQXVyNjU4MjYzMjk@._V1_SY1000_CR0,0,1499,1000_AL_.jpg</fanart>
</item>


<item>
<title>Fifty Shades Darker</title>
<meta>
<content>movie</content>
<imdb>tt4465564	</imdb>
<title>Fifty Shades Darker</title>
<year>2017</year>
</meta>
<link>
<sublink name="Stream 1 ">https://www.rapidvideo.com/v/FFMZQLVZUG</sublink>
<sublink name="Stream 2 ">http://dl.my-film.in/Movie/BluRay%20720p-x265/Fifty.Shades.Darker.2017.UNRATED.720p.BluRay.2CH.x265.HEVC-[My-Film].mkv</sublink>
<sublink name="Stream 3 ">search</sublink>
</link>
<thumbnail>https://images-na.ssl-images-amazon.com/images/M/MV5BMTQ5NTk0Njg2N15BMl5BanBnXkFtZTgwNzk5Nzk3MDI@._V1_SY1000_CR0,0,631,1000_AL_.jpg</thumbnail>
<fanart>https://images-na.ssl-images-amazon.com/images/M/MV5BMTc3NTY3OTkxMF5BMl5BanBnXkFtZTgwMjAwODk3MDI@._V1_SY1000_CR0,0,1499,1000_AL_.jpg</fanart>
</item>


<item>
<title>xXx: Return of Xander</title>
<meta>
<content>movie</content>
<imdb>tt1293847	</imdb>
<title>xXx: Return of Xander</title>
<year>2017</year>
</meta>
<link>
<sublink name="Stream 1 ">http://fastplay.cc/z3bbm96ppvcc.html</sublink>
<sublink name="Stream 2 ">search</sublink>
<sublink name="Stream 3 ">http://dl.my-film.in/Movie/BluRay%20720p/3X.Return.of.Xander.Cage.2017.720p.ShAaNiG-[My-Film].mkv</sublink>
<sublink name="Stream 4 ">https://vidlox.tv/n63g2m8rw129</sublink>
</link>
<thumbnail>https://images-na.ssl-images-amazon.com/images/M/MV5BMzcwMjkxMzQ3NV5BMl5BanBnXkFtZTgwMzgyNDA5MDI@._V1_SY1000_CR0,0,640,1000_AL_.jpg</thumbnail>
<fanart>https://images-na.ssl-images-amazon.com/images/M/MV5BMjM0OTk2MjA4MV5BMl5BanBnXkFtZTgwMzUzNDk0MDI@._V1_SY1000_CR0,0,1499,1000_AL_.jpghttps://images-na.ssl-images-amazon.com/images/M/MV5BMjM0OTk2MjA4MV5BMl5BanBnXkFtZTgwMzUzNDk0MDI@._V1_SY1000_CR0,0,1499,1000_AL_.jpg</fanart>
</item>


<item>
<title>Rings</title>
<meta>
<content>movie</content>
<imdb>tt0498381	</imdb>
<title>Rings</title>
<year>2017</year>
</meta>
<link>
<sublink name="Stream 1 ">http://dl.my-film.in/Movie/BluRay%20720p-x265/Rings.2017.720p.BluRay.2CH.x265.HEVC-[My-Film].mkv</sublink>
<sublink name="Stream 2 ">http://vidzi.tv/5o8ev0yj6fte</sublink>
<sublink name="Stream 3 ">search</sublink>
</link>
<thumbnail>https://images-na.ssl-images-amazon.com/images/M/MV5BMjE5NDI4OTYzNF5BMl5BanBnXkFtZTgwOTY1NDI4OTE@._V1_SY1000_CR0,0,640,1000_AL_.jpg</thumbnail>
<fanart>https://images-na.ssl-images-amazon.com/images/M/MV5BMGQ0MmZhMjUtYmU4MC00MjU0LTljNGQtMzNkZjQ3N2QwZjNhL2ltYWdlXkEyXkFqcGdeQXVyNjEwNTM2Mzc@._V1_SX1500_CR0,0,1500,999_AL_.jpg</fanart>
</item>


<item>
<title>Get Out</title>
<meta>
<content>movie</content>
<imdb>tt5052448	</imdb>
<title>Get Out</title>
<year>2017</year>
</meta>
<link>
<sublink name="Stream 1 ">http://fastplay.cc/nastttlqzg8t.html</sublink>
<sublink name="Stream 2 ">https://vidoza.net/kj4jpdesini9.html</sublink>
<sublink name="Stream 3 ">https://www.rapidvideo.com/v/FFO6HA8HLO</sublink>
<sublink name="Stream 4 ">https://vidlox.tv/153xgpu4bfvf</sublink>
<sublink name="Stream 5 ">search</sublink>
</link>
<thumbnail>https://images-na.ssl-images-amazon.com/images/M/MV5BNTE2Nzg1NjkzNV5BMl5BanBnXkFtZTgwOTgyODMyMTI@._V1_SY1000_CR0,0,631,1000_AL_.jpg</thumbnail>
<fanart>https://images-na.ssl-images-amazon.com/images/M/MV5BYWZkNzZhNTItMDExNy00YTljLTlmYzktOTZhYmMzNjE4MDVhXkEyXkFqcGdeQXVyMjY5ODI4NDk@._V1_SY1000_CR0,0,1611,1000_AL_.jpg</fanart>
</item>


<item>
<title>The Exception</title>
<meta>
<content>movie</content>
<imdb>tt4721124</imdb>
<title>The Exception</title>
<year>2017</year>
</meta>
<link>search</link>
<thumbnail>https://images-na.ssl-images-amazon.com/images/M/MV5BMTk4ODcyOTI3NV5BMl5BanBnXkFtZTgwMjgyOTUxMjI@._V1_SY1000_CR0,0,674,1000_AL_.jpg</thumbnail>
<fanart>https://images-na.ssl-images-amazon.com/images/M/MV5BM2E4MDAyMDYtOGYyMC00M2E1LWFhMGQtOWE2NzI1NTU4NGZjXkEyXkFqcGdeQXVyNTQ1MTYzNzY@._V1_.jpg</fanart>
</item>


<item>
<title>Table 19</title>
<meta>
<content>movie</content>
<imdb>tt1412528</imdb>
<title>Table 19</title>
<year>2017</year>
</meta>
<link>search</link>
<thumbnail>https://images-na.ssl-images-amazon.com/images/M/MV5BNzQzNzI3NzkzMl5BMl5BanBnXkFtZTgwMjA4MzczOTE@._V1_SY1000_CR0,0,676,1000_AL_.jpg</thumbnail>
<fanart>https://images-na.ssl-images-amazon.com/images/M/MV5BODAwYzJlMGEtM2NkNS00ZWJiLWJjN2QtMmY1NTRiMDNhYTNiXkEyXkFqcGdeQXVyNDg2MjUxNjM@._V1_SY1000_CR0,0,1499,1000_AL_.jpg</fanart>
</item>


<item>
<title>Once Upon a Time in Venice</title>
<meta>
<content>movie</content>
<imdb>tt4694544</imdb>
<title>Once Upon a Time in Venice</title>
<year>2017</year>
</meta>
<link>
<sublink name="Stream 1 ">https://vidlox.tv/l5dj3031xhwo</sublink>
<sublink name="Stream 2 ">search</sublink>
</link>
<thumbnail>https://images-na.ssl-images-amazon.com/images/M/MV5BMDUwZTZjN2YtMTcwNy00YjZiLWExOWMtODU4ZGZhZWY0MTE3XkEyXkFqcGdeQXVyMzQwMTY2Nzk@._V1_SY1000_CR0,0,677,1000_AL_.jpg</thumbnail>
<fanart>https://images-na.ssl-images-amazon.com/images/M/MV5BMDQ0NzUwYTQtNWYxNi00ZGE3LWJiMzktMTY3NGY3NjM1MjVkXkEyXkFqcGdeQXVyNTIzMDIwOTI@._V1_SY1000_CR0,0,1502,1000_AL_.jpg</fanart>
</item>


<item>
<title>T2 Trainspotting</title>
<meta>
<content>movie</content>
<imdb>tt2763304</imdb>
<title>T2 Trainspotting</title>
<year>2017</year>
</meta>
<link>search</link>
<thumbnail>https://images-na.ssl-images-amazon.com/images/M/MV5BMTU2NTA0NDM0MF5BMl5BanBnXkFtZTgwMDMzMTQzMTI@._V1_SY1000_CR0,0,666,1000_AL_.jpg</thumbnail>
<fanart>https://images-na.ssl-images-amazon.com/images/M/MV5BMTUyOTkyNzUwMl5BMl5BanBnXkFtZTgwNzA2NzA1MDI@._V1_SY1000_CR0,0,1333,1000_AL_.jpg</fanart>
</item>


<item>
<title>Aftermath</title>
<meta>
<content>movie</content>
<imdb>tt4581576</imdb>
<title>Aftermath</title>
<year>2017</year>
</meta>
<link>
<sublink name="Stream 1 ">https://www.rapidvideo.com/v/FGLU0ATADR</sublink>
<sublink name="Stream 2 ">search</sublink>
</link>
<thumbnail>https://images-na.ssl-images-amazon.com/images/M/MV5BMWFkYmM2ZTctNmZjZi00MWQwLWI0MjctZDdiNjJlMTlmNzdkL2ltYWdlXkEyXkFqcGdeQXVyMjM4NTM5NDY@._V1_SY1000_CR0,0,648,1000_AL_.jpg</thumbnail>
<fanart>https://images-na.ssl-images-amazon.com/images/M/MV5BOGE1ZjRmMDUtNzJkNi00ZmUyLTllMmYtNmU5ODMyZWI1MDQ4XkEyXkFqcGdeQXVyMzI1MTUzOTA@._V1_SY1000_CR0,0,1500,1000_AL_.jpg</fanart>
</item>


<item>
<title>War Machine</title>
<meta>
<content>movie</content>
<imdb>tt4758646</imdb>
<title>War Machine</title>
<year>2017</year>
</meta>
<link>
<sublink name="Stream 1 ">https://www.rapidvideo.com/v/FGLOCSRD9H</sublink>
<sublink name="Stream 2 ">search</sublink>
</link>
<thumbnail>https://images-na.ssl-images-amazon.com/images/M/MV5BMTcyMzgwNDE1M15BMl5BanBnXkFtZTgwMDAzMDM0MjI@._V1_.jpg</thumbnail>
<fanart>https://images-na.ssl-images-amazon.com/images/M/MV5BM2M1NDViZjItZTI2Yy00ZTA4LTg3ZDQtYmVmZDE1MWJkNTMyXkEyXkFqcGdeQXVyMTk5MjkzMjU@._V1_SX1777_CR0,0,1777,754_AL_.jpg</fanart>
</item>


<item>
<title>Black Butterfly</title>
<meta>
<content>movie</content>
<imdb>tt2090465</imdb>
<title>Black Butterfly</title>
<year>2017</year>
</meta>
<link>search</link>
<thumbnail>https://images-na.ssl-images-amazon.com/images/M/MV5BZTFhNWQwYWMtN2FhYS00YWFkLTgwM2QtMWMyYjVkMDY4NmNkXkEyXkFqcGdeQXVyMjM4NTM5NDY@._V1_SY1000_SX675_AL_.jpg</thumbnail>
<fanart>https://images-na.ssl-images-amazon.com/images/M/MV5BMjE0MzU0NzU0OV5BMl5BanBnXkFtZTgwNzg1NzE0MjI@._V1_SY1000_CR0,0,1505,1000_AL_.jpg</fanart>
</item>


<item>
<title>Berlin Syndrome</title>
<meta>
<content>movie</content>
<imdb>tt3335606</imdb>
<title>Berlin Syndrome</title>
<year>2017</year>
</meta>
<link>
<sublink name="Stream 1 ">https://www.rapidvideo.com/v/FGLSBDFK9X</sublink>
<sublink name="Stream 2 ">search</sublink>
</link>
<thumbnail>https://images-na.ssl-images-amazon.com/images/M/MV5BYzQ0YWRjYjctYmQ5ZC00M2M2LWE0NzMtMTI4ZDg1NjIyZTM1XkEyXkFqcGdeQXVyMTM2MzgyOTU@._V1_SY1000_SX675_AL_.jpg</thumbnail>
<fanart>https://images-na.ssl-images-amazon.com/images/M/MV5BNjM4ZThiYzYtN2E3Ny00MDg5LTgyYmEtNTQ5ZDc1YzY5OTJjXkEyXkFqcGdeQXVyNDE5MTU2MDE@._V1_.jpg</fanart>
</item>


<item>
<title>The Shack</title>
<meta>
<content>movie</content>
<imdb>tt2872518</imdb>
<title>The Shack</title>
<year>2017</year>
</meta>
<link>search</link>
<thumbnail>https://images-na.ssl-images-amazon.com/images/M/MV5BMjI3MDMxNzcxNl5BMl5BanBnXkFtZTgwODc4MzkwOTE@._V1_SY1000_CR0,0,647,1000_AL_.jpg</thumbnail>
<fanart>https://images-na.ssl-images-amazon.com/images/M/MV5BMDlhNzNmMzctMThhMi00MWRiLWE4Y2UtMjgyOGNmM2NlZDI5XkEyXkFqcGdeQXVyMjI3Mjk1ODA@._V1_SY1000_CR0,0,1500,1000_AL_.jpg</fanart>
</item>


<item>
<title>The Sense of an Ending</title>
<meta>
<content>movie</content>
<imdb>tt4827986</imdb>
<title>The Sense of an Ending</title>
<year>2017</year>
</meta>
<link>search</link>
<thumbnail>https://images-na.ssl-images-amazon.com/images/M/MV5BYzI5ZDM2NjYtNmVhMS00Y2Q4LTg5ZWUtZjUwOGNkZDJhNGY2L2ltYWdlXkEyXkFqcGdeQXVyMjM4NTM5NDY@._V1_SY1000_CR0,0,631,1000_AL_.jpg</thumbnail>
<fanart>https://images-na.ssl-images-amazon.com/images/M/MV5BMTA2MDA0OTE5NTdeQTJeQWpwZ15BbWU4MDM4MTE4NjEy._V1_SX1500_CR0,0,1500,999_AL_.jpg</fanart>
</item>


<item>
<title>Logan</title>
<meta>
<content>movie</content>
<imdb>tt3315342</imdb>
<title>Logan</title>
<year>2017</year>
</meta>
<link>
<sublink name="Stream 1 ">https://www.rapidvideo.com/v/FFN4X4XETV</sublink>
<sublink name="Stream 2 ">search</sublink>
</link>
<thumbnail>https://images-na.ssl-images-amazon.com/images/M/MV5BMjQwODQwNTg4OV5BMl5BanBnXkFtZTgwMTk4MTAzMjI@._V1_.jpg</thumbnail>
<fanart>https://images-na.ssl-images-amazon.com/images/M/MV5BZGRlYzNjOGYtZjc0Zi00ZDY4LTgyZGYtZjQ4ZjczODZhMmEwL2ltYWdlXkEyXkFqcGdeQXVyNjczOTE0MzM@._V1_.jpg</fanart>
</item>


<item>
<title>Kill Switch</title>
<meta>
<content>movie</content>
<imdb>tt5464234</imdb>
<title>Kill Switch</title>
<year>2017</year>
</meta>
<link>
<sublink name="Stream 1 ">http://fastplay.cc/u1gef0154659.html</sublink>
<sublink name="Stream 2 ">search</sublink>
</link>
<thumbnail>https://images-na.ssl-images-amazon.com/images/M/MV5BMTcxMDA4NDIxMF5BMl5BanBnXkFtZTgwMTcwMDMzMjI@._V1_SY1000_CR0,0,674,1000_AL_.jpg</thumbnail>
<fanart>https://images-na.ssl-images-amazon.com/images/M/MV5BMTgwMDExMzgzNV5BMl5BanBnXkFtZTgwMTI1ODkxMjI@._V1_.jpg</fanart>
</item>


<item>
<title>Patriots Day</title>
<meta>
<content>movie</content>
<imdb>tt4572514	</imdb>
<title>Patriots Day</title>
<year>2016</year>
</meta>
<link>
<sublink name="Stream 1 ">https://www.rapidvideo.com/v/FFM2R8SBWS</sublink>
<sublink name="Stream 2 ">https://vidlox.tv/pgofdrbeo1vu</sublink>
<sublink name="Stream 3 ">search</sublink>
</link>
<thumbnail>https://images-na.ssl-images-amazon.com/images/M/MV5BODYxMDc0NTg2Nl5BMl5BanBnXkFtZTgwNjY0NDYzOTE@._V1_SY1000_CR0,0,666,1000_AL_.jpg</thumbnail>
<fanart>https://images-na.ssl-images-amazon.com/images/M/MV5BMTUyMzM0Njk4Nl5BMl5BanBnXkFtZTgwMTQ3ODc1MDI@._V1_SY1000_SX1500_AL_.jpg</fanart>
</item>


<item>
<title>Captain America: Civil War</title>
<meta>
<content>movie</content>
<imdb>tt3498820</imdb>
<title>Captain America: Civil War</title>
<year>2016</year>
</meta>
<link>
<sublink name="Stream 1 ">https://www.rapidvideo.com/v/FGLVIN724T</sublink>
<sublink name="Stream 2 ">search</sublink>
</link>
<thumbnail>https://images-na.ssl-images-amazon.com/images/M/MV5BMjQ0MTgyNjAxMV5BMl5BanBnXkFtZTgwNjUzMDkyODE@._V1_SY1000_CR0,0,674,1000_AL_.jpg</thumbnail>
<fanart>https://fanart.tv/fanart/movies/271110/moviebackground/captain-america-3-civil-war-57b5c7fd07227.jpg</fanart>
</item>


<item>
<title>The Assignment</title>
<meta>
<content>movie</content>
<imdb>tt5034474</imdb>
<title>The Assignment</title>
<year>2016</year>
</meta>
<link>
<sublink name="Stream 1 ">https://www.rapidvideo.com/v/FGMNCY7CGC</sublink>
<sublink name="Stream 2 ">search</sublink>
</link>
<thumbnail>https://images-na.ssl-images-amazon.com/images/M/MV5BNjczMTcxOTM1NF5BMl5BanBnXkFtZTgwNjk3MTY2MTI@._V1_SY1000_CR0,0,674,1000_AL_.jpg</thumbnail>
<fanart>https://images-na.ssl-images-amazon.com/images/M/MV5BYjA2MzZjOWUtNmZjNS00OTM1LTk1NzktY2MxZDlmYTk2MmE2XkEyXkFqcGdeQXVyMjcyNzExMjE@._V1_SY1000_CR0,0,1497,1000_AL_.jpg</fanart>
</item>


<item>
<title>Money Monster</title>
<meta>
<content>movie</content>
<imdb>tt2241351</imdb>
<title>Money Monster</title>
<year>2016</year>
</meta>
<link>
<sublink name="Stream 1 ">https://www.rapidvideo.com/v/FGMWC1ZRMR</sublink>
<sublink name="Stream 2 ">search</sublink>
</link>
<thumbnail>https://images-na.ssl-images-amazon.com/images/M/MV5BMTgzMjU1NDUwMl5BMl5BanBnXkFtZTgwODg1NjY0ODE@._V1_SY1000_SX675_AL_.jpg</thumbnail>
<fanart>https://fanart.tv/fanart/movies/303858/moviebackground/money-monster-57ed46612fbac.jpg</fanart>
</item>


<item>
<title>The 5th Wave</title>
<meta>
<content>movie</content>
<imdb>tt2304933</imdb> 
<title>The 5th Wave</title>
<year>2016</year>
</meta>
<link>
<sublink name="Stream 1 ">https://www.rapidvideo.com/v/FGOPXMWQDW</sublink>
<sublink name="Stream 2 ">search</sublink>
</link>
<thumbnail>https://image.tmdb.org/t/p/w396/cgxEscv6TQRK6a514FwuJOjcqQ5.jpg</thumbnail>
<fanart>https://image.tmdb.org/t/p/w780/4obYMyIZALl7svc83fn7KelTZDp.jpg</fanart>
</item>


<item>
<title>10 Cloverfield Lane</title>
<meta>
<content>movie</content>
<imdb>tt1179933</imdb> 
<title>10 Cloverfield Lane</title>
<year>2016</year>
</meta>
<link>
<sublink name="Stream 1 ">https://www.rapidvideo.com/v/FGOQ0WZ20B</sublink>
<sublink name="Stream 2 ">search</sublink>
</link>
<thumbnail>https://image.tmdb.org/t/p/original/aeiVxTSTeGJ2ICf1iSDXkF3ivZp.jpg</thumbnail>
<fanart>https://image.tmdb.org/t/p/original/8rqJB3Nc2z5q0T6ZVXRXbAsQRGV.jpg</fanart>
</item>


<item>
<title>Allegiant</title>
<meta>
<content>movie</content>
<imdb>tt3410834</imdb> 
<title>Allegiant</title>
<year>2016</year>
</meta>
<link>
<sublink name="Stream 1 ">https://www.rapidvideo.com/v/FGOQG5ROPF</sublink>
<sublink name="Stream 2 ">search</sublink>
</link>
<thumbnail>https://image.tmdb.org/t/p/original/tSFBh9Ayn5uiwbUK9HvD2lrRgaQ.jpg</thumbnail>
<fanart>https://image.tmdb.org/t/p/original/sFthBeT0Y3WVfg6b3MkcJs9qfzq.jpg</fanart>
</item>


<item>
<title>Keanu</title>
<meta>
<content>movie</content>
<imdb>tt4139124</imdb> 
<title>Keanu</title>
<year>2016</year>
</meta>
<link>
<sublink name="Stream 1 ">https://www.rapidvideo.com/v/FGOQ7OQKOE</sublink>
<sublink name="Stream 2 ">search</sublink>
</link>
<thumbnail>https://image.tmdb.org/t/p/original/dXeRd7AlG0q1Hgc40BKJWF2LQQa.jpg</thumbnail>
<fanart>https://image.tmdb.org/t/p/original/9AjSRV8RMhHJS3DsnfJcY6CM9xU.jpg</fanart>
</item>


<item>
<title>Midnight Special</title>
<meta>
<content>movie</content>
<imdb>tt2649554</imdb> 
<title>Midnight Special</title>
<year>2016</year>
</meta>
<link>
<sublink name="Stream 1 ">https://www.rapidvideo.com/v/FGOQH9KQ1P</sublink>
<sublink name="Stream 2 ">search</sublink>
</link>
<thumbnail>https://image.tmdb.org/t/p/original/sp55ilnrp50TC0Qf7F2AC2OqxpB.jpg</thumbnail>
<fanart>https://image.tmdb.org/t/p/original/8GinyAyQrf7VYf80tcanM1jSJUB.jpg</fanart>
</item>


<item>
<title>London Has Fallen</title>
<meta>
<content>movie</content>
<imdb>tt2474932</imdb> 
<title>London Has Fallen</title>
<year>2016</year>
</meta>
<link>
<sublink name="Stream 1 ">https://www.rapidvideo.com/v/FGOQIOWSU2</sublink>
<sublink name="Stream 2 ">search</sublink>
</link>
<thumbnail>https://image.tmdb.org/t/p/original/9j2AmDhZvdwMyYKpqe4CtBkN1Tw.jpg</thumbnail>
<fanart>https://image.tmdb.org/t/p/original/3JSakCxcM7mPDhLXCPH7jnwwbXy.jpg</fanart>
</item>


<item>
<title>Criminal</title>
<meta>
<content>movie</content>
<imdb>tt3014866</imdb> 
<title>Criminal</title>
<year>2016</year>
</meta>
<link>
<sublink name="Stream 1 ">https://www.rapidvideo.com/v/FGOQ3PW626</sublink>
<sublink name="Stream 2 ">search</sublink>
</link>
<thumbnail>https://image.tmdb.org/t/p/original/6K5JOW6HmrwJnP0VILq667cspnS.jpg</thumbnail>
<fanart>https://image.tmdb.org/t/p/original/43folbQaGRpTBDbK11qq3d6qNAv.jpg</fanart>
</item>


<item>
<title>Ride Along 2</title>
<meta>
<content>movie</content>
<imdb>tt2869728</imdb> 
<title>Ride Along 2</title>
<year>2016</year>
</meta>
<link>
<sublink name="Stream 1 ">http://fastplay.cc/19rrzanll73o.html</sublink>
<sublink name="Stream 2 ">search</sublink>
</link>
<thumbnail>https://image.tmdb.org/t/p/w396/A739odgY2FjoLvYLYdypUc6GpaY.jpg</thumbnail>
<fanart>https://image.tmdb.org/t/p/w780/cnK7uPO8TKwjWz0klj1syVqO9wF.jpg</fanart>
</item>


<item>
<title>The Belko Experiment</title>
<meta>
<content>movie</content>
<imdb>tt1082807</imdb>
<title>The Belko Experiment</title>
<year>2016</year>
</meta>
<link>
<sublink name="Stream 1 ">http://fastplay.cc/p8dflw50ip2y.html</sublink>
<sublink name="Stream 2 ">search</sublink>
</link>
<thumbnail>https://images-na.ssl-images-amazon.com/images/M/MV5BODQyMDkyOTE2MF5BMl5BanBnXkFtZTgwNDQ1NTQwMTI@._V1_SY1000_CR0,0,674,1000_AL_.jpg</thumbnail>
<fanart>https://images-na.ssl-images-amazon.com/images/M/MV5BNzRkNmRhNjMtNGQ4OS00NTUzLTljMzEtYzJhZDI2OTI3ZTgwXkEyXkFqcGdeQXVyNjEwNTM2Mzc@._V1_.jpg</fanart>
</item>


<item>
<title>A Cure for Wellness</title>
<meta>
<content>movie</content>
<imdb>tt4731136</imdb>
<title>A Cure for Wellness</title>
<year>2016</year>
</meta>
<link>search</link>
<thumbnail>https://images-na.ssl-images-amazon.com/images/M/MV5BMTg5Njg1MzIwNl5BMl5BanBnXkFtZTgwNDU1NjczMDI@._V1_SY1000_SX675_AL_.jpg</thumbnail>
<fanart>https://images-na.ssl-images-amazon.com/images/M/MV5BM2U5YTcwMDAtZmI5MC00OWRiLTg1N2YtODViZGZiY2M1YzdiL2ltYWdlXkEyXkFqcGdeQXVyNjEwNTM2Mzc@._V1_.jpg</fanart>
</item>


<item>
<title>Colossal</title>
<meta>
<content>movie</content>
<imdb>tt4680182</imdb>
<title>Colossal</title>
<year>2016</year>
</meta>
<link>
<sublink name="Stream 1 ">https://www.rapidvideo.com/v/FGLZ69354J</sublink>
<sublink name="Stream 2 ">search</sublink>
</link>
<thumbnail>https://images-na.ssl-images-amazon.com/images/M/MV5BMTY2NTExOTA2MF5BMl5BanBnXkFtZTgwNTMwMjE2MTI@._V1_SY1000_CR0,0,687,1000_AL_.jpg</thumbnail>
<fanart>https://images-na.ssl-images-amazon.com/images/M/MV5BZTBkNzc0YjUtNGViYy00MjRkLWJiNTQtMTVjY2NhZWM5MTg4XkEyXkFqcGdeQXVyNTY0MTkxMTg@._V1_SY1000_CR0,0,1502,1000_AL_.jpg</fanart>
</item>


<item>
<title>Raw</title>
<meta>
<content>movie</content>
<imdb>tt5200232</imdb>
<title>Raw</title>
<year>2016</year>
</meta>
<link>search</link>
<thumbnail>https://images-na.ssl-images-amazon.com/images/M/MV5BNmEyYmRhMWYtY2I1Zi00YjBlLWI3MDQtNGU4ZTM0MDEzZDZkXkEyXkFqcGdeQXVyNjA2NDIyMzU@._V1_SY1000_CR0,0,658,1000_AL_.jpg</thumbnail>
<fanart>https://images-na.ssl-images-amazon.com/images/M/MV5BZjZkNTIxNmMtYmNlNS00MjE3LTk2N2EtZjUyYjQ3OWFmYWIxXkEyXkFqcGdeQXVyNjA2NDIyMzU@._V1_SX1777_CR0,0,1777,999_AL_.jpg</fanart>
</item>


<item>
<title>Free Fire</title>
<meta>
<content>movie</content>
<imdb>tt4158096</imdb>
<title>Free Fire</title>
<year>2016</year>
</meta>
<link>search</link>
<thumbnail>https://images-na.ssl-images-amazon.com/images/M/MV5BOWZjMDVhMDgtMTljZC00NmM0LWE1ODYtNGZmMGRhZTc3MTg2XkEyXkFqcGdeQXVyNTAzMTY4MDA@._V1_SY1000_CR0,0,675,1000_AL_.jpg</thumbnail>
<fanart>https://images-na.ssl-images-amazon.com/images/M/MV5BNWRhNGUyNjctN2U3My00NTFhLTkyNzktNTg0ODNhMGVhMDE0XkEyXkFqcGdeQXVyNjIxNDE0OTE@._V1_SX1777_CR0,0,1777,743_AL_.jpg</fanart>
</item>


<item>
<title>Spark: A Space Tail</title>
<meta>
<content>movie</content>
<imdb>tt3228088</imdb>
<title>Spark: A Space Tail</title>
<year>2016</year>
</meta>
<link>search</link>
<thumbnail>https://images-na.ssl-images-amazon.com/images/M/MV5BMTcwNzc2Mzk2M15BMl5BanBnXkFtZTgwNzU2MzA2MTI@._V1_SY1000_CR0,0,674,1000_AL_.jpg</thumbnail>
<fanart>https://images-na.ssl-images-amazon.com/images/M/MV5BZDBlNjZlOTEtZGYwMi00ZGRkLTg0M2EtZGJlNGM2ZDhkYWY5XkEyXkFqcGdeQXVyMjYwMzI5NTM@._V1_SX1777_CR0,0,1777,999_AL_.jpg</fanart>
</item>


<item>
<title>Buster's Mal Heart</title>
<meta>
<content>movie</content>
<imdb>tt5173032</imdb>
<title>Buster's Mal Heart</title>
<year>2016</year>
</meta>
<link>search</link>
<thumbnail>https://images-na.ssl-images-amazon.com/images/M/MV5BOTE4Njg2NDA5Ml5BMl5BanBnXkFtZTgwMzc1MzIwMjI@._V1_SY1000_SX675_AL_.jpg</thumbnail>
<fanart>https://images-na.ssl-images-amazon.com/images/M/MV5BYmQ3MDM2ZDAtM2ZkYS00ZGEwLTlhZDgtMGU4NGMwNmM5NDkyXkEyXkFqcGdeQXVyNjUxMjc1OTM@._V1_SX1777_CR0,0,1777,747_AL_.jpg</fanart>
</item>


<item>
<title>Underworld Blood Wars</title>
<meta>
<content>movie</content>
<imdb>tt3717252</imdb>
<title>Underworld Blood Wars</title>
<year>2016</year>
</meta>
<link>
<sublink name="Stream 1 ">http://fastplay.cc/fngddun7bb9y.html</sublink>
<sublink name="Stream 2 ">search</sublink>
</link>
<thumbnail>https://images-na.ssl-images-amazon.com/images/M/MV5BMjI5Njk0NTIyNV5BMl5BanBnXkFtZTgwNjU4MjY5MDI@._V1_SY1000_CR0,0,674,1000_AL_.jpg</thumbnail>
<fanart>https://images-na.ssl-images-amazon.com/images/M/MV5BMTUwNTcwNTY0OF5BMl5BanBnXkFtZTgwOTU4MjEwMTI@._V1_SX1500_CR0,0,1500,999_AL_.jpg</fanart>
</item>


<item>
<title>Passengers</title>
<meta>
<content>movie</content>
<imdb>tt1355644</imdb>
<title>Passengers</title>
<year>2016</year>
</meta>
<link>
<sublink name="Stream 1 ">http://fastplay.cc/mst2e413fi4f.html</sublink>
<sublink name="Stream 2 ">search</sublink>
</link>
<thumbnail>https://images-na.ssl-images-amazon.com/images/M/MV5BMTk4MjU3MDIzOF5BMl5BanBnXkFtZTgwMjM2MzY2MDI@._V1_SY1000_CR0,0,675,1000_AL_.jpg</thumbnail>
<fanart>https://images-na.ssl-images-amazon.com/images/M/MV5BNDI5ODdiZTAtMWIyZS00OTc3LTlmODItY2FiMDcxZTgxYzNjXkEyXkFqcGdeQXVyMTk5MjkzMjU@._V1_SX1777_CR0,0,1777,739_AL_.jpg</fanart>
</item>


<item>
<title>Blair Witch</title>
<meta>
<content>movie</content>
<imdb>tt1540011</imdb>
<title>Blair Witch</title>
<year>2016</year>
</meta>
<link>
<sublink name="Stream 1 ">http://fastplay.cc/978xukio96at.html</sublink>
<sublink name="Stream 2 ">search</sublink>
</link>
<thumbnail>https://images-na.ssl-images-amazon.com/images/M/MV5BMjI0NTEyMjA3NV5BMl5BanBnXkFtZTgwODk5OTU4OTE@._V1_SY1000_CR0,0,648,1000_AL_.jpg</thumbnail>
<fanart>https://fanart.tv/fanart/movies/351211/moviebackground/blair-witch-57baf4ed8e044.jpg</fanart>
</item>


<item>
<title>Snowden</title>
<meta>
<content>movie</content>
<imdb>tt3774114</imdb>
<title>Snowden</title>
<year>2016</year>
</meta>
<link>
<sublink name="Stream 1 ">http://fastplay.cc/q3mhwwuw7rm8.html</sublink>
<sublink name="Stream 2 ">search</sublink>
</link>
<thumbnail>https://images-na.ssl-images-amazon.com/images/M/MV5BMTg2MzYzNzgzOF5BMl5BanBnXkFtZTgwOTg4NzQ4OTE@._V1_SY1000_CR0,0,641,1000_AL_.jpg</thumbnail>
<fanart>https://fanart.tv/fanart/movies/302401/moviebackground/the-snowden-files-57bc2208594e4.jpg</fanart>
</item>


<item>
<title>I Am Not Your Negro</title>
<meta>
<content>movie</content>
<imdb>tt5804038</imdb>
<title>I Am Not Your Negro</title>
<year>2016</year>
</meta>
<link>
<sublink name="Stream 1 ">http://fastplay.cc/vxc001ak14fj.html</sublink>
<sublink name="Stream 2 ">search</sublink>
</link>
<thumbnail>https://images-na.ssl-images-amazon.com/images/M/MV5BMjEyNzIzMTk3Ml5BMl5BanBnXkFtZTgwNDE1Nzc1MDI@._V1_SY1000_CR0,0,674,1000_AL_.jpg</thumbnail>
<fanart>https://images-na.ssl-images-amazon.com/images/M/MV5BMjQxMDYzMDQ4N15BMl5BanBnXkFtZTgwMzg2NDEwMTI@._V1_SY1000_CR0,0,1497,1000_AL_.jpg</fanart>
</item>


<item>
<title>Ouija: Origin of Evil</title>
<meta>
<content>movie</content>
<imdb>tt4361050</imdb>
<title>Ouija: Origin of Evil</title>
<year>2016</year>
</meta>
<link>
<sublink name="Stream 1 ">https://www.rapidvideo.com/v/FGI7TD9JSO</sublink>
<sublink name="Stream 2 ">search</sublink>
</link>
<thumbnail>https://images-na.ssl-images-amazon.com/images/M/MV5BMTk4NTcxNTQ5NF5BMl5BanBnXkFtZTgwNTk5OTU4OTE@._V1_SY1000_SX675_AL_.jpg</thumbnail>
<fanart>https://fanart.tv/fanart/movies/335796/moviebackground/ouija-2-5816749878045.jpg</fanart>
</item>


<item>
<title>Doctor Strange</title>
<meta>
<content>movie</content>
<imdb>tt1211837</imdb>
<title>Doctor Strange</title>
<year>2016</year>
</meta>
<link>
<sublink name="Stream 1 ">https://www.rapidvideo.com/v/FGK38MU326</sublink>
<sublink name="Stream 2 ">search</sublink>
</link>
<thumbnail>https://images-na.ssl-images-amazon.com/images/M/MV5BNjgwNzAzNjk1Nl5BMl5BanBnXkFtZTgwMzQ2NjI1OTE@._V1_SY1000_CR0,0,674,1000_AL_.jpg</thumbnail>
<fanart>https://fanart.tv/fanart/movies/284052/moviebackground/doctor-strange-5734645f95a89.jpg</fanart>
</item>


<item>
<title>Resident Evil The Final Chapter</title>
<meta>
<content>movie</content>
<imdb>tt2592614</imdb>
<title>Resident Evil The Final Chapter</title>
<year>2016</year>
</meta>
<link>
<sublink name="Stream 1 ">https://www.rapidvideo.com/v/FGI7UP2TN7</sublink>
<sublink name="Stream 2 ">search</sublink>
</link>
<thumbnail>https://images-na.ssl-images-amazon.com/images/M/MV5BMTc0Mzc2OTQ0Ml5BMl5BanBnXkFtZTgwOTQ5MjE4MDI@._V1_SY1000_CR0,0,674,1000_AL_.jpg</thumbnail>
<fanart>https://fanart.tv/fanart/movies/173897/moviebackground/resident-evil-the-final-chapter-5877dcaa26b45.jpg</fanart>
</item>


<item>
<title>Brain on Fire</title>
<meta>
<content>movie</content>
<imdb>tt3704700</imdb>
<title>Brain on Fire</title>
<year>2016</year>
</meta>
<link>
<sublink name="Stream 1 ">https://vidlox.tv/4kpeps48du5a</sublink>
<sublink name="Stream 2 ">search</sublink>
</link>
<thumbnail>https://images-na.ssl-images-amazon.com/images/M/MV5BNmY0OThiYWQtMTAzYi00N2FiLWFlYWUtZDUzYzJiY2RlNjEwXkEyXkFqcGdeQXVyNzAwMjU2MTY@._V1_.jpg</thumbnail>
<fanart>https://images-na.ssl-images-amazon.com/images/M/MV5BY2NlNjJkMTctMDUxNy00ZDYxLWIxZDYtMGMyMjgxYzBlZWU0XkEyXkFqcGdeQXVyNzEyMTEzMjU@._V1_SY1000_CR0,0,1497,1000_AL_.jpg</fanart>
</item>







