<item>
<title>The Bone Orchard</title>
<meta>
<content>tvshow</content>
<imdb>tt1898069</imdb>
<tvdb>253573</tvdb>
<title>The Bone Orchard</title>
<year>2017</year>
</meta>
<link>
<sublink name="Stream 1 ">http://dl.funsaber.net/serial/American%20Gods/season%201/720/American.Gods.S01E01.720p.HDTV.x264.Funsaber.mkv</sublink>
<sublink name="Stream 2 ">http://dl.funsaber.net/serial/American%20Gods/season%201/480/American.Gods.S01E01.480p.HDTV.x264.Funsaber.mkv</sublink>
<sublink name="Stream 3 "></sublink>
</link>
<thumbnail>https://images-na.ssl-images-amazon.com/images/M/MV5BMzI4NDE4MDY0Ml5BMl5BanBnXkFtZTgwNzU4MzY1MTI@._V1_SY1000_CR0,0,666,1000_AL_.jpg</thumbnail>
<fanart>http://thetvdb.com/banners/fanart/original/253573-11.jpg</fanart>
</item>


<item>
<title>The Secret of Spoon</title>
<meta>
<content>tvshow</content>
<imdb>tt1898069</imdb>
<tvdb>253573</tvdb>
<title>The Secret of Spoon</title>
<year>2017</year>
</meta>
<link>
<sublink name="Stream 1 ">http://dl.funsaber.net/serial/American%20Gods/season%201/720/American.Gods.S01E02.720p.HDTV.x264.Funsaber.mkv</sublink>
<sublink name="Stream 2 ">http://dl.funsaber.net/serial/American%20Gods/season%201/480/American.Gods.S01E02.480p.HDTV.x264.Funsaber.mkv</sublink>
<sublink name="Stream 3 "></sublink>
</link>
<thumbnail>https://images-na.ssl-images-amazon.com/images/M/MV5BMzI4NDE4MDY0Ml5BMl5BanBnXkFtZTgwNzU4MzY1MTI@._V1_SY1000_CR0,0,666,1000_AL_.jpg</thumbnail>
<fanart>http://thetvdb.com/banners/fanart/original/253573-11.jpg</fanart>
</item>


<item>
<title>Head Full of Snow</title>
<meta>
<content>tvshow</content>
<imdb>tt1898069</imdb>
<tvdb>253573</tvdb>
<title>Head Full of Snow</title>
<year>2017</year>
</meta>
<link>
<sublink name="Stream 1 ">http://dl.funsaber.net/serial/American%20Gods/season%201/720/American.Gods.S01E03.720p.HDTV.x264.Funsaber.mkv</sublink>
<sublink name="Stream 2 ">http://dl.funsaber.net/serial/American%20Gods/season%201/480/American.Gods.S01E03.480p.HDTV.x264.Funsaber.mkv</sublink>
<sublink name="Stream 3 "></sublink>
</link>
<thumbnail>https://images-na.ssl-images-amazon.com/images/M/MV5BMzI4NDE4MDY0Ml5BMl5BanBnXkFtZTgwNzU4MzY1MTI@._V1_SY1000_CR0,0,666,1000_AL_.jpg</thumbnail>
<fanart>http://thetvdb.com/banners/fanart/original/253573-11.jpg</fanart>
</item>


<item>
<title>Git Gone</title>
<meta>
<content>tvshow</content>
<imdb>tt1898069</imdb>
<tvdb>253573</tvdb>
<title>Git Gone</title>
<year>2017</year>
</meta>
<link>
<sublink name="Stream 1 ">http://dl.funsaber.net/serial/American%20Gods/season%201/720/American.Gods.S01E04.720p.WEBRip.x264.Funsaber.mkv</sublink>
<sublink name="Stream 2 ">http://dl.funsaber.net/serial/American%20Gods/season%201/480/American.Gods.S01E04.480p.WEBRip.x264.Funsaber.mkv</sublink>
<sublink name="Stream 3 "></sublink>
</link>
<thumbnail>https://images-na.ssl-images-amazon.com/images/M/MV5BMzI4NDE4MDY0Ml5BMl5BanBnXkFtZTgwNzU4MzY1MTI@._V1_SY1000_CR0,0,666,1000_AL_.jpg</thumbnail>
<fanart>http://thetvdb.com/banners/fanart/original/253573-11.jpg</fanart>
</item>


<item>
<title>Lemon Scented You</title>
<meta>
<content>tvshow</content>
<imdb>tt1898069</imdb>
<tvdb>253573</tvdb>
<title>Lemon Scented You</title>
<year>2017</year>
</meta>
<link>
<sublink name="Stream 1 ">http://dl.funsaber.net/serial/American%20Gods/season%201/720/American.Gods.S01E05.720p.WEBRip.Funsaber_Net.mkv</sublink>
<sublink name="Stream 2 ">http://dl.funsaber.net/serial/American%20Gods/season%201/480/American.Gods.S01E05.480p.WEBRip.x264.Funsaber_Net.mkv</sublink>
<sublink name="Stream 3 "></sublink>
</link>
<thumbnail>https://images-na.ssl-images-amazon.com/images/M/MV5BMzI4NDE4MDY0Ml5BMl5BanBnXkFtZTgwNzU4MzY1MTI@._V1_SY1000_CR0,0,666,1000_AL_.jpg</thumbnail>
<fanart>http://thetvdb.com/banners/fanart/original/253573-11.jpg</fanart>
</item>


<item>
<title>A Murder of Gods</title>
<meta>
<content>tvshow</content>
<imdb>tt1898069</imdb>
<tvdb>253573</tvdb>
<title>A Murder of Gods</title>
<year>2017</year>
</meta>
<link>
<sublink name="Stream 1 ">http://dl.funsaber.net/serial/American%20Gods/season%201/720/American.Gods.S01E06.720p.WEBRip.Funsaber.mkv</sublink>
<sublink name="Stream 2 ">http://dl.funsaber.net/serial/American%20Gods/season%201/480/American.Gods.S01E06.480p.WEBrip.mkv</sublink>
<sublink name="Stream 3 "></sublink>
</link>
<thumbnail>https://images-na.ssl-images-amazon.com/images/M/MV5BMzI4NDE4MDY0Ml5BMl5BanBnXkFtZTgwNzU4MzY1MTI@._V1_SY1000_CR0,0,666,1000_AL_.jpg</thumbnail>
<fanart>http://thetvdb.com/banners/fanart/original/253573-11.jpg</fanart>
</item>


>>> 